tolunlun/__init__.py
tolunlun/libtolunlun.so
tolunlun-1.0.0.dist-info/METADATA
tolunlun-1.0.0.dist-info/WHEEL
tolunlun-1.0.0.dist-info/top_level.txt
tolunlun-1.0.0.dist-info/RECORD
