Metadata-Version: 2.1
Name: tolunlun
Version: 1.0.0
Summary: python packages for lunlun
Author: lixianyang
License: UNKNOWN
Platform: UNKNOWN
